{"id":"d319d83c-7d2f-4804-9c32-53739dcb2c08","title":"Presentation","mindmap":{"root":{"id":"af60e5d8-61c7-4cc6-8d67-42ab90f54d71","parentId":null,"text":{"caption":"Presentation","font":{"style":"normal","weight":"bold","decoration":"none","size":20,"color":"#000000"}},"offset":{"x":0,"y":0},"foldChildren":false,"branchColor":"#000000","children":[{"id":"fc482efe-ee71-4e9d-9513-e623f6b9a7f6","parentId":"af60e5d8-61c7-4cc6-8d67-42ab90f54d71","text":{"caption":"enthusiasm","font":{"style":"normal","weight":"normal","decoration":"none","size":15,"color":"#000000"}},"offset":{"x":168.33333333333334,"y":-151},"foldChildren":false,"branchColor":"#2f8209","children":[{"id":"1f3e1b17-208a-4100-a773-95bcd64bc064","parentId":"fc482efe-ee71-4e9d-9513-e623f6b9a7f6","text":{"caption":"exaggerate expressions","font":{"style":"normal","weight":"normal","decoration":"none","size":15,"color":"#000000"}},"offset":{"x":136,"y":32.666666666666664},"foldChildren":false,"branchColor":"#2f8209","children":[]}]},{"id":"be4ed9a4-9f8c-44e0-86ab-e68ff963c042","parentId":"af60e5d8-61c7-4cc6-8d67-42ab90f54d71","text":{"caption":"fluctuate format","font":{"style":"normal","weight":"normal","decoration":"none","size":15,"color":"#000000"}},"offset":{"x":138.33333333333334,"y":39},"foldChildren":false,"branchColor":"#2843ed","children":[{"id":"ffcfb6c6-0df4-48df-9593-0239fca712d3","parentId":"be4ed9a4-9f8c-44e0-86ab-e68ff963c042","text":{"caption":"stories","font":{"style":"normal","weight":"normal","decoration":"none","size":15,"color":"#000000"}},"offset":{"x":176.66666666666666,"y":-77.33333333333333},"foldChildren":false,"branchColor":"#2843ed","children":[]},{"id":"2e592855-0b1d-48cb-bc90-4d9f01ef6168","parentId":"be4ed9a4-9f8c-44e0-86ab-e68ff963c042","text":{"caption":"models","font":{"style":"normal","weight":"normal","decoration":"none","size":15,"color":"#000000"}},"offset":{"x":192.4375,"y":33.552083333333336},"foldChildren":false,"branchColor":"#2843ed","children":[]},{"id":"6c03350f-b94d-429e-9b54-ae679be83a7b","parentId":"be4ed9a4-9f8c-44e0-86ab-e68ff963c042","text":{"caption":"code","font":{"style":"normal","weight":"normal","decoration":"none","size":15,"color":"#000000"}},"offset":{"x":203.33333333333334,"y":-22},"foldChildren":false,"branchColor":"#2843ed","children":[]}]},{"id":"3e032a55-298d-4e3e-b883-58c59783b923","parentId":"af60e5d8-61c7-4cc6-8d67-42ab90f54d71","text":{"caption":"banish the bullet","font":{"style":"normal","weight":"normal","decoration":"none","size":15,"color":"#000000"}},"offset":{"x":136,"y":-243},"foldChildren":false,"branchColor":"#ddd98f","children":[{"id":"314215c4-11ac-46fe-9807-baca1e1d2a01","parentId":"3e032a55-298d-4e3e-b883-58c59783b923","text":{"caption":"32pt font","font":{"style":"normal","weight":"normal","decoration":"none","size":15,"color":"#000000"}},"offset":{"x":184,"y":-35},"foldChildren":false,"branchColor":"#ddd98f","children":[]},{"id":"dff7f6c1-7eaf-4940-ac4a-997814be21a8","parentId":"3e032a55-298d-4e3e-b883-58c59783b923","text":{"caption":"replace words","font":{"style":"normal","weight":"normal","decoration":"none","size":15,"color":"#000000"}},"offset":{"x":229.33333333333334,"y":28},"foldChildren":false,"branchColor":"#ddd98f","children":[{"id":"f6a6d1e4-5a52-41bf-b6a4-d5325e6f5832","parentId":"dff7f6c1-7eaf-4940-ac4a-997814be21a8","text":{"caption":"pictures","font":{"style":"normal","weight":"normal","decoration":"none","size":15,"color":"#000000"}},"offset":{"x":143.33333333333334,"y":-28.666666666666668},"foldChildren":false,"branchColor":"#ddd98f","children":[]},{"id":"13e44a92-9a22-4d6e-bd74-7f77751e0280","parentId":"dff7f6c1-7eaf-4940-ac4a-997814be21a8","text":{"caption":"animated gifs","font":{"style":"normal","weight":"normal","decoration":"none","size":15,"color":"#000000"}},"offset":{"x":166,"y":23.333333333333332},"foldChildren":false,"branchColor":"#ddd98f","children":[]},{"id":"0420a67e-cf77-454c-9b99-3d0b88b3abd4","parentId":"dff7f6c1-7eaf-4940-ac4a-997814be21a8","text":{"caption":"video (YouTube?)","font":{"style":"normal","weight":"normal","decoration":"none","size":15,"color":"#000000"}},"offset":{"x":185.33333333333334,"y":88.66666666666667},"foldChildren":false,"branchColor":"#ddd98f","children":[]},{"id":"732722ab-3a5b-4ac9-b3bd-3674bea6cc6e","parentId":"dff7f6c1-7eaf-4940-ac4a-997814be21a8","text":{"caption":"whiteboard","font":{"style":"normal","weight":"normal","decoration":"none","size":15,"color":"#000000"}},"offset":{"x":183.33333333333334,"y":-69.33333333333333},"foldChildren":false,"branchColor":"#ddd98f","children":[]}]}]},{"id":"ed45291e-17f7-4370-b42b-5dcc576eceb3","parentId":"af60e5d8-61c7-4cc6-8d67-42ab90f54d71","text":{"caption":"sizzle from the start","font":{"style":"normal","weight":"normal","decoration":"none","size":15,"color":"#000000"}},"offset":{"x":134,"y":-392},"foldChildren":false,"branchColor":"#d69975","children":[{"id":"435997a3-de9e-496a-9ae4-7dacc2207132","parentId":"ed45291e-17f7-4370-b42b-5dcc576eceb3","text":{"caption":"different from the start","font":{"style":"normal","weight":"normal","decoration":"none","size":15,"color":"#000000"}},"offset":{"x":176,"y":-73.6},"foldChildren":false,"branchColor":"#d69975","children":[{"id":"89f15896-0fad-4240-b069-59125f288ce2","parentId":"435997a3-de9e-496a-9ae4-7dacc2207132","text":{"caption":"why should you know this?","font":{"style":"normal","weight":"normal","decoration":"none","size":15,"color":"#000000"}},"offset":{"x":242,"y":-33.333333333333336},"foldChildren":false,"branchColor":"#d69975","children":[{"id":"249ba7bf-40a6-4279-b318-26e2ebaa254e","parentId":"89f15896-0fad-4240-b069-59125f288ce2","text":{"caption":"esNext","font":{"style":"normal","weight":"normal","decoration":"none","size":15,"color":"#000000"}},"offset":{"x":192.66666666666666,"y":-27.333333333333332},"foldChildren":false,"branchColor":"#d69975","children":[]}]}]},{"id":"a8760893-8244-4607-aa33-1ea644017459","parentId":"ed45291e-17f7-4370-b42b-5dcc576eceb3","text":{"caption":"first impressions","font":{"style":"normal","weight":"normal","decoration":"none","size":15,"color":"#000000"}},"offset":{"x":238,"y":-8},"foldChildren":false,"branchColor":"#d69975","children":[]},{"id":"417c5bd8-a286-4cfd-8427-d4ceecf2d9f8","parentId":"ed45291e-17f7-4370-b42b-5dcc576eceb3","text":{"caption":"engaging from the start","font":{"style":"normal","weight":"normal","decoration":"none","size":15,"color":"#000000"}},"offset":{"x":254.66666666666666,"y":40.666666666666664},"foldChildren":false,"branchColor":"#d69975","children":[]}]}]}},"dates":{"created":1603638770494,"modified":1603639270064},"dimensions":{"x":4000,"y":2000},"autosave":false}